aioqsw/__init__.py
aioqsw/const.py
aioqsw/device.py
aioqsw/exceptions.py
aioqsw/localapi.py
aioqsw/py.typed
aioqsw-0.4.2.dist-info/licenses/LICENSE
aioqsw-0.4.2.dist-info/METADATA
aioqsw-0.4.2.dist-info/WHEEL
aioqsw-0.4.2.dist-info/top_level.txt
aioqsw-0.4.2.dist-info/RECORD
