Metadata-Version: 2.4
Name: aioqsw
Version: 0.4.2
Summary: Library to control QNAP QSW devices
Author-email: Álvaro Fernández Rojas <noltari@gmail.com>
License-Expression: Apache-2.0
Project-URL: Homepage, https://github.com/Noltari/aioqsw
Project-URL: Bug Tracker, https://github.com/Noltari/aioqsw/issues
Keywords: qnap,network,switch,home
Platform: any
Classifier: Development Status :: 4 - Beta
Classifier: Intended Audience :: Developers
Classifier: Natural Language :: English
Classifier: Programming Language :: Python :: 3
Classifier: Programming Language :: Python :: 3.12
Classifier: Programming Language :: Python :: 3.13
Classifier: Topic :: Home Automation
Requires-Python: >=3.12
License-File: LICENSE
Requires-Dist: aiohttp
Dynamic: license-file
